validateall/__init__.py
validateall/validate_number.py
validateall-0.1.7.dist-info/METADATA
validateall-0.1.7.dist-info/WHEEL
validateall-0.1.7.dist-info/top_level.txt
validateall-0.1.7.dist-info/RECORD
