Metadata-Version: 2.1
Name: validateall
Version: 0.1.7
Requires-Dist: geopy (>=2.4.1)
